{
"parallel loop 1":{
"file":"example/dawncc_DRB031-truedepfirstdimension-orig-yes.c",
"function":"main",
"loop id":"2",
"loop line":"63",
"loop column":"5",
"pragma type":"parallel for",
"ordered":"false",
"offload":"true",
"multiversioned":"false",
"shared":[],
"private":[],
"firstprivate":[],
"lastprivate":[],
"linear":[],
"reduction":[],
"map to":[],
"map from":[],
"map tofrom":["b[0:1000000]"]
},
"parallel loop 2":{
"file":"example/dawncc_DRB031-truedepfirstdimension-orig-yes.c",
"function":"main",
"loop id":"1",
"loop line":"61",
"loop column":"3",
"pragma type":"parallel for",
"ordered":"false",
"offload":"true",
"multiversioned":"false",
"shared":[],
"private":[],
"firstprivate":[],
"lastprivate":[],
"linear":[],
"reduction":[],
"map to":[],
"map from":[],
"map tofrom":["b[0:1000000]"]
},
"parallel loop 3":{
"file":"example/dawncc_DRB031-truedepfirstdimension-orig-yes.c",
"function":"main",
"loop id":"3",
"loop line":"67",
"loop column":"3",
"pragma type":"NULL",
"ordered":"false",
"offload":"false",
"multiversioned":"false",
"shared":[],
"private":[],
"firstprivate":[],
"lastprivate":[],
"linear":[],
"reduction":[],
"map to":[],
"map from":[],
"map tofrom":[]
},
"parallel loop 4":{
"file":"example/dawncc_DRB031-truedepfirstdimension-orig-yes.c",
"function":"main",
"loop id":"4",
"loop line":"68",
"loop column":"5",
"pragma type":"NULL",
"ordered":"false",
"offload":"false",
"multiversioned":"false",
"shared":[],
"private":[],
"firstprivate":[],
"lastprivate":[],
"linear":[],
"reduction":[],
"map to":[],
"map from":[],
"map tofrom":[]
},
"parallel loop 5":{
"file":"example/dawncc_DRB031-truedepfirstdimension-orig-yes.c",
"function":"main",
"loop id":"5",
"loop line":"71",
"loop column":"3",
"pragma type":"NULL",
"ordered":"false",
"offload":"false",
"multiversioned":"false",
"shared":[],
"private":[],
"firstprivate":[],
"lastprivate":[],
"linear":[],
"reduction":[],
"map to":[],
"map from":[],
"map tofrom":[]
},
"parallel loop 6":{
"file":"example/dawncc_DRB031-truedepfirstdimension-orig-yes.c",
"function":"main",
"loop id":"6",
"loop line":"72",
"loop column":"5",
"pragma type":"NULL",
"ordered":"false",
"offload":"false",
"multiversioned":"false",
"shared":[],
"private":[],
"firstprivate":[],
"lastprivate":[],
"linear":[],
"reduction":[],
"map to":[],
"map from":[],
"map tofrom":[]
}
}