{
"parallel loop 1":{
"file":"example/DRB031-truedepfirstdimension-orig-yes.c",
"function":"main",
"loop id":"2",
"loop line":"66",
"loop column":"5",
"pragma type":"parallel for",
"ordered":"false",
"offload":"true",
"multiversioned":"false",
"shared":[],
"private":[],
"firstprivate":[],
"lastprivate":[],
"linear":[],
"reduction":[],
"map to":[],
"map from":["b[0:1000][0:1000]"],
"map tofrom":[]
},
"parallel loop 2":{
"file":"example/DRB031-truedepfirstdimension-orig-yes.c",
"function":"main",
"loop id":"1",
"loop line":"64",
"loop column":"3",
"pragma type":"NULL",
"ordered":"false",
"offload":"false",
"multiversioned":"false",
"shared":[],
"private":[],
"firstprivate":[],
"lastprivate":[],
"linear":[],
"reduction":[],
"map to":[],
"map from":[],
"map tofrom":[]
},
"parallel loop 3":{
"file":"example/DRB031-truedepfirstdimension-orig-yes.c",
"function":"main",
"loop id":"4",
"loop line":"75",
"loop column":"5",
"pragma type":"target parallel for",
"ordered":"false",
"offload":"true",
"multiversioned":"false",
"shared":[],
"private":[],
"firstprivate":[],
"lastprivate":[],
"linear":[],
"reduction":[],
"map to":[],
"map from":[],
"map tofrom":["b[0:1000][0:1000]"]
},
"parallel loop 4":{
"file":"example/DRB031-truedepfirstdimension-orig-yes.c",
"function":"main",
"loop id":"3",
"loop line":"73",
"loop column":"3",
"pragma type":"NULL",
"ordered":"false",
"offload":"false",
"multiversioned":"false",
"shared":[],
"private":[],
"firstprivate":[],
"lastprivate":[],
"linear":[],
"reduction":[],
"map to":[],
"map from":[],
"map tofrom":[]
},
"parallel loop 5":{
"file":"example/DRB031-truedepfirstdimension-orig-yes.c",
"function":"main",
"loop id":"6",
"loop line":"84",
"loop column":"5",
"pragma type":"parallel for",
"ordered":""true"",
"offload":"true",
"multiversioned":"false",
"shared":[],
"private":["j"],
"firstprivate":[],
"lastprivate":[],
"linear":[],
"reduction":[],
"map to":["b[0:1000][0:1000]"],
"map from":[],
"map tofrom":[]
},
"parallel loop 6":{
"file":"example/DRB031-truedepfirstdimension-orig-yes.c",
"function":"main",
"loop id":"5",
"loop line":"82",
"loop column":"3",
"pragma type":"target parallel for",
"ordered":""true"",
"offload":"true",
"multiversioned":"false",
"shared":[],
"private":["j"],
"firstprivate":[],
"lastprivate":[],
"linear":[],
"reduction":[],
"map to":["b[0:1000][0:1000]"],
"map from":[],
"map tofrom":[]
}
}